{
  "sg": {
    "country": "sg",
    "name": "Singapore",
    "supported": false,
    "collected": "2026-04-01T07:19:49.675Z"
  },
  "my": {
    "country": "my",
    "name": "Malaysia",
    "supported": false,
    "collected": "2026-04-01T07:19:53.702Z"
  },
  "th": {
    "country": "th",
    "name": "Thailand",
    "supported": false,
    "collected": "2026-04-01T07:19:58.276Z"
  },
  "ph": {
    "country": "ph",
    "name": "Philippines",
    "supported": false,
    "collected": "2026-04-01T07:20:02.522Z"
  },
  "tw": {
    "country": "tw",
    "name": "Taiwan",
    "supported": false,
    "collected": "2026-04-01T07:20:06.947Z"
  },
  "vn": {
    "country": "vn",
    "name": "Vietnam",
    "supported": false,
    "collected": "2026-04-01T07:20:11.502Z"
  },
  "br": {
    "country": "br",
    "name": "Brazil",
    "supported": false,
    "collected": "2026-04-01T07:20:14.781Z"
  },
  "mx": {
    "country": "mx",
    "name": "Mexico",
    "supported": false,
    "collected": "2026-04-01T07:20:17.985Z"
  }
}